auto_rename_ai/__init__.py
auto_rename_ai/classifier.py
auto_rename_ai/renamer.py
auto_rename_ai/utils.py
auto_rename_ai-1.0.0.dist-info/METADATA
auto_rename_ai-1.0.0.dist-info/WHEEL
auto_rename_ai-1.0.0.dist-info/top_level.txt
auto_rename_ai-1.0.0.dist-info/RECORD
