Metadata-Version: 2.4
Name: auto-rename-ai
Version: 1.0.0
Summary: AI image renamer using EfficientNetB0
Author-email: Shadi Remawi <shadiremawi7@gmail.com>
License: MIT
Requires-Python: >=3.8
Requires-Dist: numpy
Requires-Dist: pillow
Requires-Dist: tensorflow>=2.10.0
